kubectl_mcp_server-1.21.0.dist-info/licenses/LICENSE
kubectl_mcp_tool/__init__.py
kubectl_mcp_tool/__main__.py
kubectl_mcp_tool/crd_detector.py
kubectl_mcp_tool/diagnostics.py
kubectl_mcp_tool/k8s_config.py
kubectl_mcp_tool/mcp_server.py
kubectl_mcp_tool/providers.py
kubectl_mcp_tool/safety.py
kubectl_mcp_tool/auth/__init__.py
kubectl_mcp_tool/auth/config.py
kubectl_mcp_tool/auth/scopes.py
kubectl_mcp_tool/auth/verifier.py
kubectl_mcp_tool/cli/__init__.py
kubectl_mcp_tool/cli/__main__.py
kubectl_mcp_tool/cli/cli.py
kubectl_mcp_tool/cli/errors.py
kubectl_mcp_tool/cli/output.py
kubectl_mcp_tool/config/__init__.py
kubectl_mcp_tool/config/loader.py
kubectl_mcp_tool/config/schema.py
kubectl_mcp_tool/observability/__init__.py
kubectl_mcp_tool/observability/metrics.py
kubectl_mcp_tool/observability/stats.py
kubectl_mcp_tool/observability/tracing.py
kubectl_mcp_tool/prompts/__init__.py
kubectl_mcp_tool/prompts/builtin.py
kubectl_mcp_tool/prompts/custom.py
kubectl_mcp_tool/prompts/prompts.py
kubectl_mcp_tool/resources/__init__.py
kubectl_mcp_tool/resources/resources.py
kubectl_mcp_tool/tools/__init__.py
kubectl_mcp_tool/tools/backup.py
kubectl_mcp_tool/tools/browser.py
kubectl_mcp_tool/tools/capi.py
kubectl_mcp_tool/tools/certs.py
kubectl_mcp_tool/tools/cilium.py
kubectl_mcp_tool/tools/cluster.py
kubectl_mcp_tool/tools/core.py
kubectl_mcp_tool/tools/cost.py
kubectl_mcp_tool/tools/deployments.py
kubectl_mcp_tool/tools/diagnostics.py
kubectl_mcp_tool/tools/gitops.py
kubectl_mcp_tool/tools/helm.py
kubectl_mcp_tool/tools/keda.py
kubectl_mcp_tool/tools/kiali.py
kubectl_mcp_tool/tools/kind.py
kubectl_mcp_tool/tools/kubevirt.py
kubectl_mcp_tool/tools/networking.py
kubectl_mcp_tool/tools/operations.py
kubectl_mcp_tool/tools/pods.py
kubectl_mcp_tool/tools/policy.py
kubectl_mcp_tool/tools/rollouts.py
kubectl_mcp_tool/tools/security.py
kubectl_mcp_tool/tools/storage.py
kubectl_mcp_tool/tools/ui.py
kubectl_mcp_tool/tools/utils.py
kubectl_mcp_tool/tools/vind.py
kubectl_mcp_tool/utils/__init__.py
kubectl_mcp_tool/utils/helpers.py
kubectl_mcp_server-1.21.0.dist-info/METADATA
kubectl_mcp_server-1.21.0.dist-info/WHEEL
kubectl_mcp_server-1.21.0.dist-info/entry_points.txt
kubectl_mcp_server-1.21.0.dist-info/top_level.txt
kubectl_mcp_server-1.21.0.dist-info/RECORD
