Metadata-Version: 2.4
Name: kubectl-mcp-server
Version: 1.21.0
Summary: A Model Context Protocol (MCP) server for Kubernetes with 270+ tools, 8 resources, and 8 prompts
Home-page: https://github.com/rohitg00/kubectl-mcp-server
Author: Rohit Ghumare
Author-email: ghumare64@gmail.com
Project-URL: Bug Tracker, https://github.com/rohitg00/kubectl-mcp-server/issues
Project-URL: Documentation, https://github.com/rohitg00/kubectl-mcp-server#readme
Project-URL: Source, https://github.com/rohitg00/kubectl-mcp-server
Keywords: kubernetes,mcp,model-context-protocol,kubectl,helm,ai-assistant,claude,cursor,windsurf,fastmcp,devops,cloud-native,mcp-ui
Classifier: Programming Language :: Python :: 3
Classifier: Programming Language :: Python :: 3.9
Classifier: Programming Language :: Python :: 3.10
Classifier: Programming Language :: Python :: 3.11
Classifier: Programming Language :: Python :: 3.12
Classifier: License :: OSI Approved :: MIT License
Classifier: Operating System :: OS Independent
Classifier: Topic :: System :: Systems Administration
Classifier: Topic :: Software Development :: Libraries :: Python Modules
Classifier: Intended Audience :: Developers
Classifier: Intended Audience :: System Administrators
Requires-Python: >=3.9
License-File: LICENSE
Requires-Dist: fastmcp>=3.0.0b1
Requires-Dist: pydantic>=2.0.0
Requires-Dist: fastapi>=0.100.0
Requires-Dist: uvicorn>=0.22.0
Requires-Dist: starlette>=0.27.0
Requires-Dist: kubernetes>=28.1.0
Requires-Dist: PyYAML>=6.0.1
Requires-Dist: requests>=2.31.0
Requires-Dist: urllib3>=2.1.0
Requires-Dist: websocket-client>=1.7.0
Requires-Dist: jsonschema>=4.20.0
Requires-Dist: cryptography>=42.0.2
Requires-Dist: rich>=13.0.0
Requires-Dist: aiohttp>=3.8.0
Requires-Dist: aiohttp-sse>=2.1.0
Provides-Extra: ui
Requires-Dist: mcp-ui-server>=0.5.0; extra == "ui"
Provides-Extra: all
Requires-Dist: mcp-ui-server>=0.5.0; extra == "all"
Dynamic: author
Dynamic: author-email
Dynamic: classifier
Dynamic: description
Dynamic: description-content-type
Dynamic: home-page
Dynamic: keywords
Dynamic: license-file
Dynamic: project-url
Dynamic: provides-extra
Dynamic: requires-dist
Dynamic: requires-python
Dynamic: summary
